IQSmart/IQSmart.py
IQSmart/__init__.py
IQSmart/defaultCalData.py
IQSmart-1.2.15.dist-info/LICENSE
IQSmart-1.2.15.dist-info/METADATA
IQSmart-1.2.15.dist-info/WHEEL
IQSmart-1.2.15.dist-info/top_level.txt
IQSmart-1.2.15.dist-info/RECORD
