Metadata-Version: 2.1
Name: IQSmart
Version: 1.2.15
Summary: Theia MCR motor control functions and calculations
Author-email: Mark Peterson <mpeterson@theiatech.com>
Project-URL: Homepage, https://github.com/cliquot22/IQSmart
Project-URL: Bug Tracker, https://github.com/cliquot22/IQSmart/issues
Classifier: Development Status :: 5 - Production/Stable
Classifier: Intended Audience :: Science/Research
Classifier: Intended Audience :: Manufacturing
Classifier: License :: Other/Proprietary License
Classifier: Operating System :: Microsoft :: Windows
Classifier: Programming Language :: Python :: 3
Classifier: Natural Language :: English
Requires-Python: >=3.7
License-File: LICENSE
Requires-Dist: numpy
Requires-Dist: scipy
Requires-Dist: TheiaMCR
